README.rst
resellerclub.py
setup.py
resellerclub.egg-info/PKG-INFO
resellerclub.egg-info/SOURCES.txt
resellerclub.egg-info/dependency_links.txt
resellerclub.egg-info/entry_points.txt
resellerclub.egg-info/requires.txt
resellerclub.egg-info/top_level.txt