Metadata-Version: 1.1
Name: resellerclub
Version: 0.1.3
Summary: ResellerClub API CLI client
Home-page: https://github.com/miracle2k/resellerclub-python
Author: Michael Elsdörfer
Author-email: michael@elsdoerfer.com
License: BSD
Platform: UNKNOWN
Classifier: Development Status :: 3 - Alpha
Classifier: Intended Audience :: Developers
Classifier: License :: OSI Approved :: BSD License
Classifier: Operating System :: OS Independent
Classifier: Programming Language :: Python
